sphinxcontrib/proof/__init__.py
sphinxcontrib_proof-1.7.0.dist-info/AUTHORS
sphinxcontrib_proof-1.7.0.dist-info/LICENSE
sphinxcontrib_proof-1.7.0.dist-info/METADATA
sphinxcontrib_proof-1.7.0.dist-info/WHEEL
sphinxcontrib_proof-1.7.0.dist-info/top_level.txt
sphinxcontrib_proof-1.7.0.dist-info/zip-safe
sphinxcontrib_proof-1.7.0.dist-info/RECORD
