Metadata-Version: 2.1
Name: sphinxcontrib-proof
Version: 1.7.0
Summary: This packages contains the Proof sphinx extension, which provides directives to typeset theorems, lemmas, proofs, etc.
Home-page: https://framagit.org/spalax/sphinxcontrib-proof
Author: Louis Paternault
Author-email: spalax@gresille.org
License: AGPLv3 or any later version
Project-URL: Documentation, http://sphinxcontrib-proof.readthedocs.io
Project-URL: Source, https://framagit.org/spalax/sphinxcontrib-proof
Project-URL: Tracker, https://framagit.org/spalax/sphinxcontrib-proof/issues
Keywords: sphinx math proof theorem
Classifier: Development Status :: 5 - Production/Stable
Classifier: Framework :: Sphinx :: Extension
Classifier: Intended Audience :: Developers
Classifier: License :: OSI Approved :: GNU Affero General Public License v3 or later (AGPLv3+)
Classifier: Operating System :: Unix
Classifier: Programming Language :: Python :: 3
Classifier: Programming Language :: Python :: 3.8
Classifier: Programming Language :: Python :: 3.9
Classifier: Programming Language :: Python :: 3.10
Classifier: Programming Language :: Python :: 3.11
Classifier: Programming Language :: Python :: 3.12
Classifier: Programming Language :: Python :: 3.13
Classifier: Topic :: Documentation :: Sphinx
Classifier: Topic :: Scientific/Engineering :: Mathematics
Classifier: Topic :: Software Development :: Libraries :: Python Modules
Requires-Python: <4,>=3.8
License-File: LICENSE
License-File: AUTHORS
Requires-Dist: jinja2
Requires-Dist: sphinx>=1.8.0
